<?xml version="1.0" encoding="UTF-8"?>
<!DOCTYPE seqopcodes SYSTEM "seqopcodes.dtd">
<seqopcodes>
    <!-- OLD OPCODES - these need updating still post 1/26/2005 

    <opcode id="02a5" name="OP_UserCompInfo" updated="02/10/04">
        <comment>User submitted computer information</comment>
    </opcode>
    <opcode id="02db" name="OP_LoginComplete" updated="02/10/04">
        <comment></comment>
    </opcode>
-->


    <opcode id="75dd" name="OP_SendLoginInfo" updated="12/07/05">
        <comment>Client starting world session by asking for login information</comment>
    </opcode>
    <opcode id="0701" name="OP_LogServer" updated="12/07/05">
        <comment></comment>
    </opcode>
    <opcode id="04ec" name="OP_ExpansionInfo" updated="12/07/05">
        <comment>Which expansions user has</comment>
    </opcode>
    <opcode id="30f6" name="OP_ApproveWorld" updated="12/07/05">
        <comment></comment>
    </opcode>
    <opcode id="3853" name="OP_EnterWorld" updated="12/07/05">
        <comment>Server approval for client to enter world</comment>
    </opcode>
    <opcode id="497c" name="OP_SendCharInfo" updated="12/07/05">
        <comment>Send all chars visible @ char select</comment>
    </opcode>
    <opcode id="7d37" name="OP_World_Client_CRC1" updated="12/07/05">
        <comment>Contains a snippet of spell data</comment>
    </opcode>
    <opcode id="2717" name="OP_World_Client_CRC2" updated="12/07/05">
        <comment>Second client verification packet</comment>
    </opcode>
    <opcode id="1a85" name="OP_MOTD" updated="12/07/05">
        <comment>old MOTDCode Server message of the day</comment>
        <payload dir="server" typename="worldMOTDStruct" sizechecktype="none"/>
    </opcode>
    <opcode id="6957" name="OP_GuildList" updated="12/07/05">
        <comment>old GuildListCode</comment>
        <payload dir="server" typename="worldGuildListStruct" sizechecktype="match"/>
    </opcode>
    <opcode id="53e1" name="OP_SetChatServer" updated="12/07/05">
        <comment>Chatserver? IP,Port,servername.Charname,password(?)</comment>
    </opcode>
    <opcode id="3f0d" name="OP_SetChatServer2" updated="12/07/05">
        <comment>Chatserver? IP,Port,servername.Charname,password(?)</comment>
    </opcode>
    <opcode id="4886" name="OP_ZoneServerInfo" updated="12/07/05">
        <comment>old ZoneServerInfo</comment>
    </opcode>
    <opcode id="2ec6" name="OP_WorldComplete" updated="12/07/05">
        <comment>Client telling world server it is done. World replies by disconnecting.</comment>
    </opcode>

    <opcode id="26c9" name="OP_DeleteCharacter" updated="10/27/05">
        <comment>Delete character @ char select</comment>
    </opcode>
    <opcode id="6160" name="OP_CharacterCreate" updated="06/29/04">
        <comment>Create character @ char select</comment>
    </opcode>
    <opcode id="3ea6" name="OP_ApproveName" updated="10/27/04">
        <comment>Approving new character name @ char creation</comment>
    </opcode>
    <opcode id="23d4" name="OP_RandomNameGenerator" updated="06/29/05">
        <comment>Returns a random name</comment>
    </opcode>
</seqopcodes>
